deepmatch/__init__.py
deepmatch/inputs.py
deepmatch/utils.py
deepmatch/layers/__init__.py
deepmatch/layers/core.py
deepmatch/layers/interaction.py
deepmatch/layers/sequence.py
deepmatch/models/__init__.py
deepmatch/models/comirec.py
deepmatch/models/dssm.py
deepmatch/models/fm.py
deepmatch/models/mind.py
deepmatch/models/ncf.py
deepmatch/models/sdm.py
deepmatch/models/youtubednn.py
deepmatch-0.3.1.dist-info/LICENSE
deepmatch-0.3.1.dist-info/METADATA
deepmatch-0.3.1.dist-info/WHEEL
deepmatch-0.3.1.dist-info/top_level.txt
deepmatch-0.3.1.dist-info/RECORD
