Metadata-Version: 2.1
Name: deepmatch
Version: 0.3.1
Summary: Deep matching model library for recommendations, advertising. It's easy to train models and to **export representation vectors** for user and item which can be used for **ANN search**.
Home-page: https://github.com/shenweichen/deepmatch
Author: Weichen Shen
Author-email: weichenswc@163.com
License: Apache-2.0
Download-URL: https://github.com/shenweichen/deepmatch/tags
Keywords: match,matching,recommendationdeep learning,tensorflow,tensor,keras
Platform: UNKNOWN
Classifier: License :: OSI Approved :: Apache Software License
Classifier: Operating System :: OS Independent
Classifier: Intended Audience :: Developers
Classifier: Intended Audience :: Education
Classifier: Intended Audience :: Science/Research
Classifier: Programming Language :: Python :: 3
Classifier: Programming Language :: Python :: 3.6
Classifier: Programming Language :: Python :: 3.7
Classifier: Programming Language :: Python :: 3.8
Classifier: Programming Language :: Python :: 3.9
Classifier: Programming Language :: Python :: 3.10
Classifier: Topic :: Scientific/Engineering
Classifier: Topic :: Scientific/Engineering :: Artificial Intelligence
Classifier: Topic :: Software Development
Classifier: Topic :: Software Development :: Libraries
Classifier: Topic :: Software Development :: Libraries :: Python Modules
Requires-Python: >=2.7,!=3.0.*,!=3.1.*,!=3.2.*,!=3.3.*,!=3.4.*
Requires-Dist: requests
Requires-Dist: deepctr (~=0.9.2)
Provides-Extra: cpu
Requires-Dist: tensorflow (>=1.9.0) ; extra == 'cpu'
Provides-Extra: gpu
Requires-Dist: tensorflow-gpu (>=1.9.0) ; extra == 'gpu'
